regadgets/__init__.py
regadgets/bases/__init__.py
regadgets/bases/base45.py
regadgets/bases/base58.py
regadgets/bases/base62.py
regadgets/bases/base65536.py
regadgets/bases/base91.py
regadgets/bases/bases.py
regadgets/bases/py3base92.py
regadgets/bits/__init__.py
regadgets/bits/bits.py
regadgets/bits/cstyle.py
regadgets/bruteforce/__init__.py
regadgets/bruteforce/bruteforcer.py
regadgets/crypto/__init__.py
regadgets/crypto/aes.py
regadgets/crypto/blowfish.py
regadgets/crypto/bxors.py
regadgets/crypto/rc4.py
regadgets/crypto/sm4.py
regadgets/crypto/tea.py
regadgets/crypto/xtea.py
regadgets/crypto/xxtea.py
regadgets/math/__init__.py
regadgets/math/dct.py
regadgets/math/matrix.py
regadgets/rands/__init__.py
regadgets/rands/rands.py
regadgets/trans/__init__.py
regadgets/trans/sbox.py
regadgets/utils/__init__.py
regadgets/utils/cython_helper.py
regadgets/utils/z3util.py
regadgets-2.0.2.dist-info/LICENSE
regadgets-2.0.2.dist-info/METADATA
regadgets-2.0.2.dist-info/WHEEL
regadgets-2.0.2.dist-info/top_level.txt
regadgets-2.0.2.dist-info/RECORD
