Metadata-Version: 2.2
Name: regadgets
Version: 2.0.2
Summary: A Python Package For Reverse Engineering.
Author-email: Steesha <jsteesha@gmail.com>
License: GNU General Public License v3 (GPLv3)
Project-URL: Homepage, https://github.com/Steesha/regadgets
Project-URL: Changelog, https://github.com/Steesha/regadgets/blob/main/CHANGELOG.md
Keywords: reverse,tool,gadgets,reverse engineering
Classifier: Programming Language :: Python :: 3
Classifier: License :: OSI Approved :: GNU General Public License v3 (GPLv3)
Classifier: Intended Audience :: Developers
Requires-Python: >=3.8
License-File: LICENSE
Requires-Dist: z3-solver>=4.13.0.0
Requires-Dist: base2048>=0.1.3
Requires-Dist: six>=1.16.0
